pwgazer-1.0.0.dist-info/METADATA
pwgazer-1.0.0.dist-info/WHEEL
pwgazer-1.0.0.dist-info/entry_points.txt
pwgazer-1.0.0.dist-info/licenses/LICENSE
pwgazer/__init__.py
pwgazer/app/CameraCalibration.py
pwgazer/app/CameraSelector.py
pwgazer/app/OfflineCalibration.py
pwgazer/app/OfflineTracker.py
pwgazer/app/RealtimeTracker.py
pwgazer/app/ScreenLayout.py
pwgazer/app/__init__.py
pwgazer/app/_dialogs.py
pwgazer/app/_util.py
pwgazer/app/img/screen_layout.png
pwgazer/app/tracker.cfg
pwgazer/core/config.py
pwgazer/core/data.py
pwgazer/core/eye.py
pwgazer/core/face.py
pwgazer/core/iris_detectors/__init__.py
pwgazer/core/iris_detectors/enet.onnx
pwgazer/core/iris_detectors/enet_detector.py
pwgazer/core/iris_detectors/ert_detector.py
pwgazer/core/iris_detectors/ert_predictor.dat
pwgazer/core/iris_detectors/peak_detector.py
pwgazer/core/resources/CameraParam.cfg
pwgazer/core/resources/CameraParamHD.cfg
pwgazer/core/resources/FaceModel.cfg
pwgazer/core/resources/FaceModel_Female_JP.cfg
pwgazer/core/resources/FaceModel_Infant.cfg
pwgazer/core/resources/FaceModel_Male_JP.cfg
pwgazer/core/resources/FilterParam.cfg
pwgazer/core/resources/checker8x5.pdf
pwgazer/core/resources/shape_predictor_68_face_landmarks.dat
pwgazer/core/screen.py
pwgazer/core/util.py
pwgazer/demo/CalibrationDemo.py
pwgazer/demo/OfflineCalibrationDemo.py
pwgazer/tools/FrameInspector.py
pwgazer/tools/PerformanceTest.py
pwgazer-1.0.0.dist-info/RECORD
