Metadata-Version: 2.1
Name: pwgazer
Version: 1.0.0
Summary: Python-based Wide-angle GAZE Recorder
Author-Email: Hiroyuki Sogo <hsogo12600@gmail.com>>
Maintainer-Email: Hiroyuki Sogo <hsogo12600@gmail.com>>
Classifier: Development Status :: 4 - Beta
Classifier: Operating System :: Microsoft :: Windows
Classifier: Operating System :: POSIX :: Linux
Classifier: Programming Language :: Python :: 3
Classifier: Topic :: Scientific/Engineering
Classifier: License :: OSI Approved :: GNU General Public License v3 or later (GPLv3+)
Project-URL: Homepage, https://github.com/hsogo/pwgazer
Requires-Python: >=3.8
Requires-Dist: numpy; sys_platform != "win32"
Requires-Dist: numpy<2.0; sys_platform == "win32"
Requires-Dist: scipy
Requires-Dist: wxpython
Requires-Dist: dlib; sys_platform != "win32"
Requires-Dist: dlib-binary; sys_platform == "win32"
Requires-Dist: onnxruntime; sys_platform != "win32"
Requires-Dist: onnxruntime==1.20.1; sys_platform == "win32"
Requires-Dist: opencv-python; sys_platform != "win32"
Requires-Dist: opencv-python<4.12; sys_platform == "win32"
